CHANGES.rst
CONTRIBUTORS.rst
MANIFEST.in
README.rst
setup.cfg
setup.py
docs/LICENSE.GPL
docs/LICENSE.rst
docs/index.rst
src/collective/__init__.py
src/collective.pamfixes.egg-info/PKG-INFO
src/collective.pamfixes.egg-info/SOURCES.txt
src/collective.pamfixes.egg-info/dependency_links.txt
src/collective.pamfixes.egg-info/entry_points.txt
src/collective.pamfixes.egg-info/namespace_packages.txt
src/collective.pamfixes.egg-info/not-zip-safe
src/collective.pamfixes.egg-info/requires.txt
src/collective.pamfixes.egg-info/top_level.txt
src/collective/pamfixes/__init__.py
src/collective/pamfixes/configure.zcml
src/collective/pamfixes/interfaces.py
src/collective/pamfixes/overrides.zcml
src/collective/pamfixes/setuphandlers.py
src/collective/pamfixes/testing.py
src/collective/pamfixes/testing.zcml
src/collective/pamfixes/viewlets.py
src/collective/pamfixes/profiles/testfixture/collectivepamfixes_testfixture_marker.txt
src/collective/pamfixes/profiles/testfixture/metadata.xml
src/collective/pamfixes/profiles/testfixture/portal_languages.xml
src/collective/pamfixes/templates/alternate-languages.pt
src/collective/pamfixes/tests/__init__.py
src/collective/pamfixes/tests/test_viewlet.py