Metadata-Version: 1.1
Name: collective.pamfixes
Version: 1.0
Summary: An add-on for Plone that patches the alternate languages viewlet in plone.app.multilingual to fix a bug in the generation of the relative URLs that are used for the rel="alternate" links on multilingual pages.
Home-page: https://github.com/collective/collective.pamfixes
Author: Zach Cashero
Author-email: zach@propertyshelf.com
License: GPL version 2
Download-URL: https://pypi.python.org/pypi/collective.pamfixes
Keywords: Python Plone
Platform: UNKNOWN
Classifier: Environment :: Web Environment
Classifier: Framework :: Plone
Classifier: Framework :: Plone :: 4.1
Classifier: Framework :: Plone :: 4.2
Classifier: Framework :: Plone :: 4.3
Classifier: Framework :: Plone :: 5.0
Classifier: Programming Language :: Python
Classifier: Programming Language :: Python :: 2.6
Classifier: Programming Language :: Python :: 2.7
Classifier: Operating System :: OS Independent
Classifier: License :: OSI Approved :: GNU General Public License v2 (GPLv2)
